[
  {
    "referrer": "Google",
    "count": 177,
    "uniques": 136
  },
  {
    "referrer": "github.com",
    "count": 61,
    "uniques": 44
  },
  {
    "referrer": "1point3acres.com",
    "count": 16,
    "uniques": 11
  },
  {
    "referrer": "reddit.com",
    "count": 6,
    "uniques": 5
  },
  {
    "referrer": "analyticsindiamag.com",
    "count": 5,
    "uniques": 4
  },
  {
    "referrer": "github.com.cnpmjs.org",
    "count": 5,
    "uniques": 3
  },
  {
    "referrer": "blog.etereo.io",
    "count": 4,
    "uniques": 3
  },
  {
    "referrer": "qiita.com",
    "count": 4,
    "uniques": 1
  },
  {
    "referrer": "medium.com",
    "count": 1,
    "uniques": 1
  },
  {
    "referrer": "news.ycombinator.com",
    "count": 1,
    "uniques": 1
  }
]