[
  {
    "referrer": "Google",
    "count": 281,
    "uniques": 141
  },
  {
    "referrer": "github.com",
    "count": 121,
    "uniques": 79
  },
  {
    "referrer": "linkedin.com",
    "count": 101,
    "uniques": 73
  },
  {
    "referrer": "firmai.org",
    "count": 59,
    "uniques": 21
  },
  {
    "referrer": "t.co",
    "count": 19,
    "uniques": 12
  },
  {
    "referrer": "m.facebook.com",
    "count": 16,
    "uniques": 13
  },
  {
    "referrer": "reddit.com",
    "count": 16,
    "uniques": 11
  },
  {
    "referrer": "DuckDuckGo",
    "count": 9,
    "uniques": 3
  },
  {
    "referrer": "Bing",
    "count": 6,
    "uniques": 2
  },
  {
    "referrer": "l.facebook.com",
    "count": 5,
    "uniques": 4
  }
]