[
  {
    "path": "/firmai/atspy",
    "title": "GitHub - firmai/atspy: AtsPy: Automated Time Series Models in Python (by @fir...",
    "count": 247,
    "uniques": 109
  },
  {
    "path": "/firmai/atspy/issues/12",
    "title": "\"ERROR: Could not find a version that satisfies the requirement dataclasses==...",
    "count": 164,
    "uniques": 138
  },
  {
    "path": "/firmai/atspy/issues",
    "title": "Issues · firmai/atspy · GitHub",
    "count": 43,
    "uniques": 11
  },
  {
    "path": "/firmai/atspy/blob/master/requirements.txt",
    "title": "atspy/requirements.txt at master · firmai/atspy · GitHub",
    "count": 23,
    "uniques": 10
  },
  {
    "path": "/firmai/atspy/issues/7",
    "title": "Installation issue · Issue #7 · firmai/atspy · GitHub",
    "count": 18,
    "uniques": 12
  },
  {
    "path": "/firmai/atspy/tree/master/atspy",
    "title": "atspy/atspy at master · firmai/atspy · GitHub",
    "count": 11,
    "uniques": 9
  },
  {
    "path": "/firmai/atspy/issues/2",
    "title": "need requirements.txt · Issue #2 · firmai/atspy · GitHub",
    "count": 6,
    "uniques": 4
  },
  {
    "path": "/firmai/atspy/search",
    "title": "Search · arima",
    "count": 6,
    "uniques": 1
  },
  {
    "path": "/firmai/atspy/tree/master/atspy_files",
    "title": "atspy/atspy_files at master · firmai/atspy · GitHub",
    "count": 5,
    "uniques": 4
  },
  {
    "path": "/firmai/atspy/issues/18",
    "title": "Key error when using ensemble · Issue #18 · firmai/atspy",
    "count": 5,
    "uniques": 1
  }
]