[
  {
    "referrer": "Google",
    "count": 892,
    "uniques": 497
  },
  {
    "referrer": "github.com",
    "count": 182,
    "uniques": 95
  },
  {
    "referrer": "kaggle.com",
    "count": 102,
    "uniques": 71
  },
  {
    "referrer": "DuckDuckGo",
    "count": 19,
    "uniques": 15
  },
  {
    "referrer": "t.co",
    "count": 7,
    "uniques": 1
  },
  {
    "referrer": "firmai.org",
    "count": 6,
    "uniques": 5
  },
  {
    "referrer": "cn.bing.com",
    "count": 5,
    "uniques": 5
  },
  {
    "referrer": "reddit.com",
    "count": 4,
    "uniques": 4
  },
  {
    "referrer": "Bing",
    "count": 4,
    "uniques": 3
  },
  {
    "referrer": "mail.google.com",
    "count": 4,
    "uniques": 2
  }
]